{
  "start": [
    [
      [
        2560,
        307
      ],
      0
    ],
    [
      [
        2560,
        483
      ],
      0
    ],
    [
      [
        2460,
        307
      ],
      0
    ],
    [
      [
        2460,
        483
      ],
      0
    ],
    [
      [
        2360,
        307
      ],
      0
    ],
    [
      [
        2360,
        483
      ],
      0
    ],
    [
      [
        2260,
        307
      ],
      0
    ],
    [
      [
        2260,
        483
      ],
      0
    ]
  ],
  "start_line": [
    [
      2686,
      218
    ],
    [
      2687,
      549
    ]
  ],
  "checks": [
    [
      [
        2686,
        218
      ],
      [
        2687,
        549
      ]
    ],
    [
      [
        3539,
        230
      ],
      [
        3491,
        562
      ]
    ],
    [
      [
        4039,
        813
      ],
      [
        4254,
        548
      ]
    ],
    [
      [
        3586,
        1206
      ],
      [
        3655,
        1555
      ]
    ],
    [
      [
        2184,
        1267
      ],
      [
        2306,
        1585
      ]
    ],
    [
      [
        2141,
        1751
      ],
      [
        1805,
        1752
      ]
    ],
    [
      [
        2328,
        1953
      ],
      [
        2198,
        2295
      ]
    ],
    [
      [
        3987,
        1983
      ],
      [
        3975,
        2322
      ]
    ],
    [
      [
        4502,
        2662
      ],
      [
        4811,
        2502
      ]
    ],
    [
      [
        4193,
        3186
      ],
      [
        4374,
        3486
      ]
    ],
    [
      [
        3044,
        3375
      ],
      [
        2996,
        3729
      ]
    ],
    [
      [
        1845,
        3104
      ],
      [
        1790,
        3448
      ]
    ],
    [
      [
        949,
        3288
      ],
      [
        834,
        3704
      ]
    ],
    [
      [
        722,
        2815
      ],
      [
        1067,
        2833
      ]
    ],
    [
      [
        1040,
        1423
      ],
      [
        818,
        1156
      ]
    ],
    [
      [
        1370,
        862
      ],
      [
        1753,
        918
      ]
    ],
    [
      [
        1547,
        547
      ],
      [
        1123,
        308
      ]
    ],
    [
      [
        2082,
        211
      ],
      [
        2107,
        559
      ]
    ]
  ],
  "laps": 7,
  "lap_record": [
    "PJ",
    15901.0
  ]
}